{"title":"Body","body":{"required":true,"content":{"application/json":{"schema":{"type":"object","required":["type","payload"],"properties":{"type":{"type":"string","example":"sendMedia"},"payload":{"type":"object","required":["number","mediatype","media","filename"],"properties":{"number":{"type":"string","example":"51987654321"},"mediatype":{"type":"string","example":"document"},"media":{"type":"string","example":"https://example.com/contrato.pdf"},"caption":{"type":"string","example":"Adjunto el contrato"},"mimetype":{"type":"string","example":"application/pdf"},"filename":{"type":"string","example":"contrato.pdf"},"delay":{"type":"integer","example":1200}}}}},"example":{"type":"sendMedia","payload":{"number":"51987654321","mediatype":"document","media":"https://example.com/contrato.pdf","caption":"Adjunto el contrato","mimetype":"application/pdf","filename":"contrato.pdf","delay":1200}}}}}}